{"type": "Feature", "id": 56051803, "properties": {"woe:id": 56051803, "woe:parent_id": 592215, "woe:name": "A\u00e9rodrome D'albertville", "woe:placetype": 14, "woe:placetype_name": "Airport", "woe:lang": "FRE", "iso:country": "FR", "meta:provider": ["geoplanet:7.3.1", "geoplanet:7.3.2", "geoplanet:7.4.0", "geoplanet:7.4.1", "geoplanet:7.5.1", "geoplanet:7.5.2", "geoplanet:7.6.0", "geoplanet:7.8.1", "geoplanet:7.9.0", "geoplanet:7.10.0", "geoplanet:8.0.0", "woeplanet:8.0.0"], "meta:indexed": "2020-08-20T20:53:41.947859", "meta:updated": "2020-08-22T01:53:17.197006", "woe:alias_FRE_S": ["Aerodrome D'albertville"], "woe:hierarchy": {"continent": 24865675, "country": 23424819, "town": 0, "planet": 1, "county": 12597180, "suburb": 0, "state": 7153329, "region": 0, "localadmin": 12671768}, "woe:timezone_id": 28350911, "woe:hash": "u0he842hg85e", "woe:centroid": [6.32828, 45.62841], "geom:latitude": 45.62841, "geom:longitude": 6.32828, "geom:hash": "u0he842hg85e", "woe:latitude": 45.62841, "geom:centroid": [6.32828, 45.62841], "woe:longitude": 6.32828, "woe:repo": "woeplanet-airport-fr"}, "geometry": {"coordinates": [6.32828, 45.62841], "type": "Point"}}