{"type": "Feature", "id": 56051833, "geometry": {"type": "Point", "coordinates": [-0.519, 45.964741]}, "properties": {"woe:id": 56051833, "woe:parent_id": 624708, "woe:name": "A\u00e9rodrome de Saint-jean-d'ang\u00e9ly", "woe:placetype": 14, "woe:placetype_name": "Airport", "woe:lang": "FRE", "iso:country": "FR", "meta:provider": ["geoplanet:7.3.1", "geoplanet:7.3.2", "geoplanet:7.4.0", "geoplanet:7.4.1", "geoplanet:7.5.1", "geoplanet:7.5.2", "geoplanet:7.6.0", "geoplanet:7.8.1", "geoplanet:7.9.0", "geoplanet:7.10.0", "geoplanet:8.0.0", "woeplanet:8.0.0"], "meta:indexed": "2020-08-20T20:53:41.972773", "meta:updated": "2020-10-14T11:26:50.986343", "woe:alias_FRE_S": ["Aerodrome de Saint-jean-d'angely"], "woe:hierarchy": {"continent": 24865675, "country": 23424819, "town": 0, "planet": 1, "county": 12597189, "suburb": 0, "state": 7153327, "region": 0, "localadmin": 12670639}, "woe:timezone_id": 28350911, "woe:hash": "gbptkpwh42v8", "woe:centroid": [-0.519, 45.964741], "geom:latitude": 45.964741, "geom:longitude": -0.519, "geom:hash": "gbptkpwh42v8", "woe:latitude": 45.964741, "geom:centroid": [-0.519, 45.964741], "woe:longitude": -0.519, "woe:repo": "woeplanet-airport-fr", "geom:area": 0.0, "woe:scale": 19}}