{"type": "Feature", "id": 22656450, "properties": {"woe:id": 22656450, "woe:parent_id": 623662, "woe:name": "Aerodrome de Saint-Cyr-L'ecole", "woe:placetype": 14, "woe:placetype_name": "Airport", "woe:lang": "ENG", "iso:country": "FR", "meta:provider": ["geoplanet:7.3.1", "geoplanet:7.3.2", "geoplanet:7.4.0", "geoplanet:7.4.1", "geoplanet:7.5.1", "geoplanet:7.5.2", "geoplanet:7.6.0", "geoplanet:7.8.1", "geoplanet:7.9.0", "geoplanet:7.10.0", "geoplanet:8.0.0", "woeplanet:8.0.0"], "meta:indexed": "2020-08-20T20:53:41.766763", "meta:updated": "2020-08-22T01:53:17.104674", "woe:alias_FRE_V": ["A\u00e9rodrome de Saint-Cyr-l'\u00c9cole"], "woe:hierarchy": {"continent": 24865675, "country": 23424819, "town": 0, "planet": 1, "county": 12597126, "suburb": 0, "state": 7153319, "region": 0, "localadmin": 12652355}, "woe:timezone_id": 28350911, "woe:hash": "u09mxhvhgg40", "woe:centroid": [2.07246, 48.806221], "geom:latitude": 48.806221, "geom:longitude": 2.07246, "geom:hash": "u09mxhvhgg40", "woe:latitude": 48.806221, "geom:centroid": [2.07246, 48.806221], "woe:longitude": 2.07246, "woe:repo": "woeplanet-airport-fr"}, "geometry": {"coordinates": [2.07246, 48.806221], "type": "Point"}}