{"type": "Feature", "id": 12512854, "geometry": {"type": "Point", "coordinates": [4.2619, 46.968601]}, "properties": {"woe:id": 12512854, "woe:parent_id": 577451, "woe:name": "Bellevue Airport", "woe:placetype": 14, "woe:placetype_name": "Airport", "woe:lang": "ENG", "iso:country": "FR", "meta:provider": ["geoplanet:7.3.1", "geoplanet:7.3.2", "geoplanet:7.4.0", "geoplanet:7.4.1", "geoplanet:7.5.1", "geoplanet:7.5.2", "geoplanet:7.6.0", "geoplanet:7.8.1", "geoplanet:7.9.0", "geoplanet:7.10.0", "geoplanet:8.0.0", "woeplanet:8.0.0"], "meta:indexed": "2020-08-20T20:53:41.712505", "meta:updated": "2020-10-14T11:26:51.077025", "woe:hierarchy": {"continent": 24865675, "country": 23424819, "town": 0, "planet": 1, "county": 12597153, "suburb": 0, "state": 7153312, "region": 0, "localadmin": 12637783}, "woe:timezone_id": 28350911, "woe:hash": "u0750yr7vmyf", "woe:centroid": [4.2619, 46.968601], "geom:latitude": 46.968601, "geom:longitude": 4.2619, "geom:hash": "u0750yr7vmyf", "woe:latitude": 46.968601, "geom:centroid": [4.2619, 46.968601], "woe:longitude": 4.2619, "woe:repo": "woeplanet-airport-fr", "geom:area": 0.0, "woe:scale": 19}}