{"type": "Feature", "id": 56051859, "geometry": {"type": "Point", "coordinates": [0.43903, 42.796249]}, "properties": {"woe:id": 56051859, "woe:parent_id": 576726, "woe:name": "Altiport de Peyresourde-balestas", "woe:placetype": 14, "woe:placetype_name": "Airport", "woe:lang": "FRE", "iso:country": "FR", "meta:provider": ["geoplanet:7.3.1", "geoplanet:7.3.2", "geoplanet:7.4.0", "geoplanet:7.4.1", "geoplanet:7.5.1", "geoplanet:7.5.2", "geoplanet:7.6.0", "geoplanet:7.8.1", "geoplanet:7.9.0", "geoplanet:7.10.0", "geoplanet:8.0.0", "woeplanet:8.0.0"], "meta:indexed": "2020-08-20T20:53:41.994718", "meta:updated": "2020-10-14T11:26:50.942793", "woe:hierarchy": {"continent": 24865675, "country": 23424819, "town": 0, "planet": 1, "county": 12597169, "suburb": 0, "state": 7153323, "region": 0, "localadmin": 12665840}, "woe:timezone_id": 28350911, "woe:hash": "sp873yzdnph3", "woe:centroid": [0.43903, 42.796249], "geom:latitude": 42.796249, "geom:longitude": 0.43903, "geom:hash": "sp873yzdnph3", "woe:latitude": 42.796249, "geom:centroid": [0.43903, 42.796249], "woe:longitude": 0.43903, "woe:repo": "woeplanet-airport-fr", "geom:area": 0.0, "woe:scale": 19}}