{"type": "Feature", "id": 12512938, "properties": {"woe:id": 12512938, "woe:parent_id": 611554, "woe:name": "Mimizan Airport", "woe:placetype": 14, "woe:placetype_name": "Airport", "woe:lang": "ENG", "iso:country": "FR", "meta:provider": ["geoplanet:7.3.1", "geoplanet:7.3.2", "geoplanet:7.4.0", "geoplanet:7.4.1", "geoplanet:7.5.1", "geoplanet:7.5.2", "geoplanet:7.6.0", "geoplanet:7.8.1", "geoplanet:7.9.0", "geoplanet:7.10.0", "geoplanet:8.0.0", "woeplanet:8.0.0"], "meta:indexed": "2020-08-20T20:53:41.829781", "meta:updated": "2020-08-22T01:53:17.138341", "woe:hierarchy": {"continent": 24865675, "country": 23424819, "town": 0, "planet": 1, "county": 12597149, "suburb": 0, "state": 7153309, "region": 0, "localadmin": 12649205}, "woe:timezone_id": 28350911, "woe:hash": "ezz5jkx7qt3m", "woe:centroid": [-1.1653, 44.1464], "geom:latitude": 44.1464, "geom:longitude": -1.1653, "geom:hash": "ezz5jkx7qt3m", "woe:latitude": 44.1464, "geom:centroid": [-1.1653, 44.1464], "woe:longitude": -1.1653, "woe:repo": "woeplanet-airport-fr"}, "geometry": {"coordinates": [-1.1653, 44.1464], "type": "Point"}}