{"type": "Feature", "id": 56051875, "properties": {"woe:id": 56051875, "woe:parent_id": 602247, "woe:name": "A\u00e9rodr. de B\u00e9darieux-la-tour/orb", "woe:placetype": 14, "woe:placetype_name": "Airport", "woe:lang": "FRE", "iso:country": "FR", "meta:provider": ["geoplanet:7.3.1", "geoplanet:7.3.2", "geoplanet:7.4.0", "geoplanet:7.4.1", "geoplanet:7.5.1", "geoplanet:7.5.2", "geoplanet:7.6.0", "geoplanet:7.8.1", "geoplanet:7.9.0", "geoplanet:7.10.0", "geoplanet:8.0.0", "woeplanet:8.0.0"], "meta:indexed": "2020-08-20T20:53:42.008196", "meta:updated": "2020-08-22T01:53:17.224726", "woe:alias_FRE_S": ["Aerodr. de Bedarieux-la-tour/orb"], "woe:hierarchy": {"continent": 24865675, "country": 23424819, "town": 0, "planet": 1, "county": 12597179, "suburb": 0, "state": 7153320, "region": 0, "localadmin": 12657621}, "woe:timezone_id": 28350911, "woe:hash": "spf0pxd0e770", "woe:centroid": [3.14498, 43.635052], "geom:latitude": 43.635052, "geom:longitude": 3.14498, "geom:hash": "spf0pxd0e770", "woe:latitude": 43.635052, "geom:centroid": [3.14498, 43.635052], "woe:longitude": 3.14498, "woe:repo": "woeplanet-airport-fr"}, "geometry": {"coordinates": [3.14498, 43.635052], "type": "Point"}}