{"type": "Feature", "id": 12512975, "geometry": {"type": "Point", "coordinates": [6.3625, 47.784698]}, "properties": {"woe:id": 12512975, "woe:parent_id": 578422, "woe:name": "St Sauveur Airport", "woe:placetype": 14, "woe:placetype_name": "Airport", "woe:lang": "ENG", "iso:country": "FR", "meta:provider": ["geoplanet:7.3.1", "geoplanet:7.3.2", "geoplanet:7.4.0", "geoplanet:7.4.1", "geoplanet:7.5.1", "geoplanet:7.5.2", "geoplanet:7.6.0", "geoplanet:7.8.1", "geoplanet:7.9.0", "geoplanet:7.10.0", "geoplanet:8.0.0", "woeplanet:8.0.0"], "meta:indexed": "2020-08-20T20:53:41.741790", "meta:updated": "2020-10-14T11:26:51.143330", "woe:hierarchy": {"continent": 24865675, "country": 23424819, "town": 0, "planet": 1, "county": 12597119, "suburb": 0, "state": 7153317, "region": 0, "localadmin": 12638242}, "woe:timezone_id": 28350911, "woe:hash": "u0kxbfcn0crf", "woe:centroid": [6.3625, 47.784698], "geom:latitude": 47.784698, "geom:longitude": 6.3625, "geom:hash": "u0kxbfcn0crf", "woe:latitude": 47.784698, "geom:centroid": [6.3625, 47.784698], "woe:longitude": 6.3625, "woe:repo": "woeplanet-airport-fr", "geom:area": 0.0, "woe:scale": 19}}