{"type": "Feature", "id": 12512892, "geometry": {"type": "Point", "coordinates": [7.62773, 48.544949]}, "properties": {"woe:id": 12512892, "woe:parent_id": 589717, "woe:name": "A\u00e9roport International Strasbourg", "woe:placetype": 14, "woe:placetype_name": "Airport", "woe:lang": "FRE", "iso:country": "FR", "meta:provider": ["geoplanet:7.3.1", "geoplanet:7.3.2", "geoplanet:7.4.0", "geoplanet:7.4.1", "geoplanet:7.5.1", "geoplanet:7.5.2", "geoplanet:7.6.0", "geoplanet:7.8.1", "geoplanet:7.9.0", "geoplanet:7.10.0", "geoplanet:8.0.0", "woeplanet:8.0.0"], "meta:indexed": "2020-08-20T20:53:41.802766", "woe:alias_FIN_V": ["Strasbourgin Lentokentta", "Strasbourgin Lentokentt\u00e5", "Strasbourgin Lentoasema"], "woe:alias_DUT_V": ["Inter Luchthaven Straasburg", "Luchthaven Strasbourg", "Inter. Luchthaven Straatsburg"], "woe:alias_POR_V": ["Aeroporto Inter de Estrasburgo", "Aerop. Internacional de Estrasburgo"], "meta:updated": "2020-10-14T11:26:51.074596", "woe:alias_FRE_S": ["Aeroport SXB", "SXB Aeroport", "Aeroport de Strasbourg", "Aeroport Strasbourg", "Aeroport de Strasbourg Entzheim"], "woe:alias_GER_V": ["Inter Flughafen Strasbourg", "Flughafen Stra\u00dfburg"], "woe:alias_FRE_V": ["A\u00e9roport de Strasbourg", "A\u00e9roport Strasbourg", "A\u00e9roport SXB", "SXB A\u00e9roport", "Aeroport Strasbourg International", "A\u00e9roport Strasbourg International", "Strasbourg Entzheim", "A\u00e9roport de Strasbourg Entzheim", "A\u00e9roport Strasbourg Entzheim"], "woe:alias_GER_S": ["Flughafen Strassburg"], "woe:alias_SPA_V": ["Aeropuerto Inter de Strasbourg", "Aeropuerto de Estrasburgo"], "woe:alias_ENG_V": ["Entzheim Airport", "SXB Airport", "SXB", "Strasbourg International Airport"], "woe:alias_ITA_V": ["Aeroporto Inter Di Strasburgo", "Aeroporto Internaz. di Strasburgo"], "woe:alias_ENG_P": ["Strasbourg Airport"], "woe:alias_DAN_V": ["Strasbourg Internationale Lufthavn"], "woe:alias_UNK_V": ["Mezinarodni Letiste Strasbourg", "Medzinarodne Letisko Strasburg", "\u0394\u03b9\u03b5\u03b8\u03bd\u03b5\u03c3 \u0391\u03b5\u03c1\u03bf\u03b4\u03c1\u03bf\u03bc\u03b9\u03bf \u03a3\u03c4\u03c1\u03b1\u03c3\u03b2\u03bf\u03c5\u03c1\u03b3\u03bf\u03c5", "\u0394\u03b9\u03b5\u03b8\u03bd\u03b5\u03c3 \u0391\u03b5\u03c1\u03bf\u03b4\u03c1\u03bfmu\u03b9\u03bf \u03a3\u03c4\u03c1\u03b1\u03c3\u03b2\u03bf\u03c5\u03c1\u03b3\u03bf\u03c5", "\u0410\u044d\u0440\u043e\u043f\u043e\u0440\u0442 \u0421\u0442\u0440\u0430\u0441\u0431\u0443\u0440\u0433 \u041c\u0435\u0436\u0434\u0443\u043d\u0430\u0440\u043e\u0434\u043d\u044b\u0438", "\u0410\u044d\u0440\u043e\u043f\u043e\u0440\u0442 \u0421\u0442\u0440\u0430\u0441\u0431\u0443\u0440\u0433 \u041c\u0435\u0436\u0434\u0443\u043d\u0430\u0440\u043e\u0434\u043d\u044b\u0439"], "woe:alias_NOR_V": ["Strasbourg Internasjonale Lufthavn"], "woe:alias_SWE_V": ["Strasbourg Inter Flygplats"], "woe:alias_ITA_Q": ["Aeroporto di Strasburgo"], "woe:alias_HUN_V": ["Strassburgi Nemzetkozi Repuloter", "Strassburgi Nemzetk\u00f6zi Rep\u00fcl\u0151t\u00e9r"], "woe:alias_POL_V": ["Port Lotniczy Strasburg"], "woe:alias_CZE_V": ["Mezin\u00e1rodn\u00ed Leti\u0161t\u011b \u0160trasburk", "Mezinarodni Letiste Strasburk"], "woe:hierarchy": {"continent": 24865675, "country": 23424819, "town": 0, "planet": 1, "county": 12597135, "suburb": 0, "state": 7153330, "region": 0, "localadmin": 12643326}, "woe:timezone_id": 28350911, "woe:hash": "u0tkjt66ffrs", "woe:centroid": [7.62773, 48.544949], "geom:latitude": 48.544949, "geom:longitude": 7.62773, "geom:hash": "u0tkjt66ffrs", "woe:latitude": 48.544949, "geom:centroid": [7.62773, 48.544949], "woe:longitude": 7.62773, "woe:repo": "woeplanet-airport-fr", "geom:area": 0.0, "woe:scale": 19}}