{"type": "Feature", "id": 12512914, "geometry": {"type": "Point", "coordinates": [1.50022, 43.58736]}, "properties": {"woe:id": 12512914, "woe:parent_id": 577980, "woe:name": "Lasbordes Airport", "woe:placetype": 14, "woe:placetype_name": "Airport", "woe:lang": "ENG", "iso:country": "FR", "meta:provider": ["geoplanet:7.3.1", "geoplanet:7.3.2", "geoplanet:7.4.0", "geoplanet:7.4.1", "geoplanet:7.5.1", "geoplanet:7.5.2", "geoplanet:7.6.0", "geoplanet:7.8.1", "geoplanet:7.9.0", "geoplanet:7.10.0", "geoplanet:8.0.0", "woeplanet:8.0.0"], "meta:indexed": "2020-08-20T20:53:41.815763", "woe:alias_ENG_V": ["Aerodrome Balma-Lasbordes"], "meta:updated": "2020-10-14T11:26:51.142301", "woe:hierarchy": {"continent": 24865675, "country": 23424819, "town": 0, "planet": 1, "county": 12597186, "suburb": 0, "state": 7153323, "region": 0, "localadmin": 12656160}, "woe:timezone_id": 28350911, "woe:hash": "sp9pfnu6v8v4", "woe:centroid": [1.50022, 43.58736], "geom:latitude": 43.58736, "geom:longitude": 1.50022, "geom:hash": "sp9pfnu6v8v4", "woe:latitude": 43.58736, "geom:centroid": [1.50022, 43.58736], "woe:longitude": 1.50022, "woe:repo": "woeplanet-airport-fr", "geom:area": 0.0, "woe:scale": 19}}