{"type": "Feature", "id": 56051860, "properties": {"woe:id": 56051860, "woe:parent_id": 620181, "woe:name": "A\u00e9rodrome de P\u00e9zenas-nizas", "woe:placetype": 14, "woe:placetype_name": "Airport", "woe:lang": "FRE", "iso:country": "FR", "meta:provider": ["geoplanet:7.3.1", "geoplanet:7.3.2", "geoplanet:7.4.0", "geoplanet:7.4.1", "geoplanet:7.5.1", "geoplanet:7.5.2", "geoplanet:7.6.0", "geoplanet:7.8.1", "geoplanet:7.9.0", "geoplanet:7.10.0", "geoplanet:8.0.0", "woeplanet:8.0.0"], "meta:indexed": "2020-08-20T20:53:41.995534", "meta:updated": "2020-08-22T01:53:17.220270", "woe:alias_FRE_S": ["Aerodrome de Pezenas-nizas"], "woe:hierarchy": {"continent": 24865675, "country": 23424819, "town": 0, "planet": 1, "county": 12597179, "suburb": 0, "state": 7153320, "region": 0, "localadmin": 12667634}, "woe:timezone_id": 28350911, "woe:hash": "spdrmxek3zp2", "woe:centroid": [3.41031, 43.50388], "geom:latitude": 43.50388, "geom:longitude": 3.41031, "geom:hash": "spdrmxek3zp2", "woe:latitude": 43.50388, "geom:centroid": [3.41031, 43.50388], "woe:longitude": 3.41031, "woe:repo": "woeplanet-airport-fr"}, "geometry": {"coordinates": [3.41031, 43.50388], "type": "Point"}}