{"type": "Feature", "id": 12512940, "properties": {"woe:id": 12512940, "woe:parent_id": 612114, "woe:name": "Mont de Marsan Airport", "woe:placetype": 14, "woe:placetype_name": "Airport", "woe:lang": "ENG", "iso:country": "FR", "meta:provider": ["geoplanet:7.3.1", "geoplanet:7.3.2", "geoplanet:7.4.0", "geoplanet:7.4.1", "geoplanet:7.5.1", "geoplanet:7.5.2", "geoplanet:7.6.0", "geoplanet:7.8.1", "geoplanet:7.9.0", "geoplanet:7.10.0", "geoplanet:8.0.0", "woeplanet:8.0.0"], "meta:indexed": "2020-08-20T20:53:41.731711", "woe:alias_ENG_V": ["MDM Airport", "MDM"], "meta:updated": "2020-08-22T01:53:17.087399", "woe:alias_FRE_S": ["MDM Aeroport", "Aeroport MDM"], "woe:alias_FRE_V": ["A\u00e9roport MDM", "MDM A\u00e9roport"], "woe:hierarchy": {"continent": 24865675, "country": 23424819, "town": 0, "planet": 1, "county": 12597149, "suburb": 0, "state": 7153309, "region": 0, "localadmin": 12649362}, "woe:timezone_id": 28350911, "woe:hash": "ezz9u3yknqke", "woe:centroid": [-0.5075, 43.911701], "geom:latitude": 43.911701, "geom:longitude": -0.5075, "geom:hash": "ezz9u3yknqke", "woe:latitude": 43.911701, "geom:centroid": [-0.5075, 43.911701], "woe:longitude": -0.5075, "woe:repo": "woeplanet-airport-fr"}, "geometry": {"coordinates": [-0.5075, 43.911701], "type": "Point"}}