{"type": "Feature", "id": 56051787, "properties": {"woe:id": 56051787, "woe:parent_id": 584905, "woe:name": "A\u00e9rodrome de Ch\u00e2teau-arnoux", "woe:placetype": 14, "woe:placetype_name": "Airport", "woe:lang": "FRE", "iso:country": "FR", "meta:provider": ["geoplanet:7.3.1", "geoplanet:7.3.2", "geoplanet:7.4.0", "geoplanet:7.4.1", "geoplanet:7.5.1", "geoplanet:7.5.2", "geoplanet:7.6.0", "geoplanet:7.8.1", "geoplanet:7.9.0", "geoplanet:7.10.0", "geoplanet:8.0.0", "woeplanet:8.0.0"], "meta:indexed": "2020-08-20T20:53:41.934604", "meta:updated": "2020-08-22T01:53:17.190152", "woe:alias_FRE_S": ["Aerodrome de Chateau-arnoux"], "woe:hierarchy": {"continent": 24865675, "country": 23424819, "town": 0, "planet": 1, "county": 12597191, "suburb": 0, "state": 7153328, "region": 0, "localadmin": 22755981}, "woe:timezone_id": 28350911, "woe:hash": "spu68mdwq3zr", "woe:centroid": [5.99126, 44.064499], "geom:latitude": 44.064499, "geom:longitude": 5.99126, "geom:hash": "spu68mdwq3zr", "woe:latitude": 44.064499, "geom:centroid": [5.99126, 44.064499], "woe:longitude": 5.99126, "woe:repo": "woeplanet-airport-fr"}, "geometry": {"coordinates": [5.99126, 44.064499], "type": "Point"}}