{"type": "Feature", "id": 12512894, "geometry": {"type": "Point", "coordinates": [7.0117, 47.655602]}, "properties": {"woe:id": 12512894, "woe:parent_id": 591321, "woe:name": "Fontaine Airport", "woe:placetype": 14, "woe:placetype_name": "Airport", "woe:lang": "ENG", "iso:country": "FR", "meta:provider": ["geoplanet:7.3.1", "geoplanet:7.3.2", "geoplanet:7.4.0", "geoplanet:7.4.1", "geoplanet:7.5.1", "geoplanet:7.5.2", "geoplanet:7.6.0", "geoplanet:7.8.1", "geoplanet:7.9.0", "geoplanet:7.10.0", "geoplanet:8.0.0", "woeplanet:8.0.0"], "meta:indexed": "2020-08-20T20:53:41.725115", "woe:alias_ENG_V": ["BOR Airport", "BOR"], "meta:updated": "2020-10-14T11:26:51.073772", "woe:alias_FRE_S": ["BOR Aeroport", "Aeroport BOR"], "woe:alias_FRE_V": ["A\u00e9roport BOR", "BOR A\u00e9roport"], "woe:hierarchy": {"continent": 24865675, "country": 23424819, "town": 0, "planet": 1, "county": 12597154, "suburb": 0, "state": 7153317, "region": 0, "localadmin": 12643930}, "woe:timezone_id": 28350911, "woe:hash": "u0kzpe3y02n6", "woe:centroid": [7.0117, 47.655602], "geom:latitude": 47.655602, "geom:longitude": 7.0117, "geom:hash": "u0kzpe3y02n6", "woe:latitude": 47.655602, "geom:centroid": [7.0117, 47.655602], "woe:longitude": 7.0117, "woe:repo": "woeplanet-airport-fr", "geom:area": 0.0, "woe:scale": 19}}