{"type": "Feature", "id": 12512950, "properties": {"woe:id": 12512950, "woe:parent_id": 616539, "woe:name": "Pierrefeu Airport", "woe:placetype": 14, "woe:placetype_name": "Airport", "woe:lang": "ENG", "iso:country": "FR", "meta:provider": ["geoplanet:7.3.1", "geoplanet:7.3.2", "geoplanet:7.4.0", "geoplanet:7.4.1", "geoplanet:7.5.1", "geoplanet:7.5.2", "geoplanet:7.6.0", "geoplanet:7.8.1", "geoplanet:7.9.0", "geoplanet:7.10.0", "geoplanet:8.0.0", "woeplanet:8.0.0"], "meta:indexed": "2020-08-20T20:53:41.836630", "woe:alias_FRE_Q": ["Aerodrome de Cuers-Pierrefeu"], "meta:updated": "2020-08-22T01:53:17.140871", "woe:alias_FRE_V": ["A\u00e9rodrome de Cuers-Pierrefeu"], "woe:hierarchy": {"continent": 24865675, "country": 23424819, "town": 0, "planet": 1, "county": 12597187, "suburb": 0, "state": 7153328, "region": 0, "localadmin": 12667501}, "woe:timezone_id": 28350911, "woe:hash": "spsmgr5zvgn3", "woe:centroid": [6.12479, 43.238041], "geom:latitude": 43.238041, "geom:longitude": 6.12479, "geom:hash": "spsmgr5zvgn3", "woe:latitude": 43.238041, "geom:centroid": [6.12479, 43.238041], "woe:longitude": 6.12479, "woe:repo": "woeplanet-airport-fr"}, "geometry": {"coordinates": [6.12479, 43.238041], "type": "Point"}}