{"type": "Feature", "id": 56051822, "properties": {"woe:id": 56051822, "woe:parent_id": 626775, "woe:name": "A\u00e9rodrome Le Havre-saint-romain", "woe:placetype": 14, "woe:placetype_name": "Airport", "woe:lang": "FRE", "iso:country": "FR", "meta:provider": ["geoplanet:7.3.1", "geoplanet:7.3.2", "geoplanet:7.4.0", "geoplanet:7.4.1", "geoplanet:7.5.1", "geoplanet:7.5.2", "geoplanet:7.6.0", "geoplanet:7.8.1", "geoplanet:7.9.0", "geoplanet:7.10.0", "geoplanet:8.0.0", "woeplanet:8.0.0"], "meta:indexed": "2020-08-20T20:53:41.963566", "meta:updated": "2020-08-22T01:53:17.205118", "woe:alias_FRE_S": ["Aerodrome Le Havre-saint-romain"], "woe:hierarchy": {"continent": 24865675, "country": 23424819, "town": 0, "planet": 1, "county": 12597115, "suburb": 0, "state": 7153318, "region": 0, "localadmin": 12644588}, "woe:timezone_id": 28350911, "woe:hash": "u0b3b54jjw7d", "woe:centroid": [0.35455, 49.543739], "geom:latitude": 49.543739, "geom:longitude": 0.35455, "geom:hash": "u0b3b54jjw7d", "woe:latitude": 49.543739, "geom:centroid": [0.35455, 49.543739], "woe:longitude": 0.35455, "woe:repo": "woeplanet-airport-fr"}, "geometry": {"coordinates": [0.35455, 49.543739], "type": "Point"}}