{"type": "Feature", "id": 12512877, "geometry": {"type": "Point", "coordinates": [4.82505, 46.827728]}, "properties": {"woe:id": 12512877, "woe:parent_id": 20215748, "woe:name": "A\u00e9roport Chalon-Champforgeuil", "woe:placetype": 14, "woe:placetype_name": "Airport", "woe:lang": "FRE", "iso:country": "FR", "meta:provider": ["geoplanet:7.3.1", "geoplanet:7.3.2", "geoplanet:7.4.0", "geoplanet:7.4.1", "geoplanet:7.5.1", "geoplanet:7.5.2", "geoplanet:7.6.0", "geoplanet:7.8.1", "geoplanet:7.9.0", "geoplanet:7.10.0", "geoplanet:8.0.0", "woeplanet:8.0.0"], "meta:indexed": "2020-08-20T20:53:41.720146", "meta:updated": "2020-10-14T11:26:51.075385", "woe:alias_ENG_P": ["Champforgeuil Airport"], "woe:alias_FRE_S": ["Aeroport Chalon-Champforgeuil"], "woe:hierarchy": {"continent": 24865675, "country": 23424819, "town": 0, "planet": 1, "county": 12597153, "suburb": 0, "state": 7153312, "region": 0, "localadmin": 12646414}, "woe:timezone_id": 28350911, "woe:hash": "u076mu9rrc4n", "woe:centroid": [4.82505, 46.827728], "geom:latitude": 46.827728, "geom:longitude": 4.82505, "geom:hash": "u076mu9rrc4n", "woe:latitude": 46.827728, "geom:centroid": [4.82505, 46.827728], "woe:longitude": 4.82505, "woe:repo": "woeplanet-airport-fr", "geom:area": 0.0, "woe:scale": 19}}