{"type": "Feature", "id": 12512924, "geometry": {"type": "Point", "coordinates": [1.6989, 43.090801]}, "properties": {"woe:id": 12512924, "woe:parent_id": 607242, "woe:name": "Les Pujols Airport", "woe:placetype": 14, "woe:placetype_name": "Airport", "woe:lang": "ENG", "iso:country": "FR", "meta:provider": ["geoplanet:7.3.1", "geoplanet:7.3.2", "geoplanet:7.4.0", "geoplanet:7.4.1", "geoplanet:7.5.1", "geoplanet:7.5.2", "geoplanet:7.6.0", "geoplanet:7.8.1", "geoplanet:7.9.0", "geoplanet:7.10.0", "geoplanet:8.0.0", "woeplanet:8.0.0"], "meta:indexed": "2020-08-20T20:53:41.821554", "meta:updated": "2020-10-14T11:26:51.116661", "woe:hierarchy": {"continent": 24865675, "country": 23424819, "town": 0, "planet": 1, "county": 12597197, "suburb": 0, "state": 7153323, "region": 0, "localadmin": 12665486}, "woe:timezone_id": 28350911, "woe:hash": "sp9jnsmn55x8", "woe:centroid": [1.6989, 43.090801], "geom:latitude": 43.090801, "geom:longitude": 1.6989, "geom:hash": "sp9jnsmn55x8", "woe:latitude": 43.090801, "geom:centroid": [1.6989, 43.090801], "woe:longitude": 1.6989, "woe:repo": "woeplanet-airport-fr", "geom:area": 0.0, "woe:scale": 19}}