{"type": "Feature", "id": 12523805, "geometry": {"type": "Point", "coordinates": [-0.86416, 47.079899]}, "properties": {"woe:id": 12523805, "woe:parent_id": 585927, "woe:name": "Le Pontrea Airport", "woe:placetype": 14, "woe:placetype_name": "Airport", "woe:lang": "ENG", "iso:country": "FR", "meta:provider": ["geoplanet:7.3.1", "geoplanet:7.3.2", "geoplanet:7.4.0", "geoplanet:7.4.1", "geoplanet:7.5.1", "geoplanet:7.5.2", "geoplanet:7.6.0", "geoplanet:7.8.1", "geoplanet:7.9.0", "geoplanet:7.10.0", "geoplanet:8.0.0", "woeplanet:8.0.0"], "meta:indexed": "2020-08-20T20:53:41.752356", "woe:alias_ENG_V": ["CET Airport", "Le Pontrea", "CET"], "meta:updated": "2020-10-14T11:26:51.172564", "woe:alias_FRE_S": ["Aeroport CET", "CET Aeroport"], "woe:alias_FRE_V": ["A\u00e9roport CET", "CET A\u00e9roport"], "woe:hierarchy": {"continent": 24865675, "country": 23424819, "town": 0, "planet": 1, "county": 12597202, "suburb": 0, "state": 7153325, "region": 0, "localadmin": 12659455}, "woe:timezone_id": 28350911, "woe:hash": "gbr7u6dsr978", "woe:centroid": [-0.86416, 47.079899], "geom:latitude": 47.079899, "geom:longitude": -0.86416, "geom:hash": "gbr7u6dsr978", "woe:latitude": 47.079899, "geom:centroid": [-0.86416, 47.079899], "woe:longitude": -0.86416, "woe:repo": "woeplanet-airport-fr", "geom:area": 0.0, "woe:scale": 19}}