{"type": "Feature", "id": 56051808, "properties": {"woe:id": 56051808, "woe:parent_id": 581998, "woe:name": "A\u00e9rodrome de Lyon-brindas", "woe:placetype": 14, "woe:placetype_name": "Airport", "woe:lang": "FRE", "iso:country": "FR", "meta:provider": ["geoplanet:7.3.1", "geoplanet:7.3.2", "geoplanet:7.4.0", "geoplanet:7.4.1", "geoplanet:7.5.1", "geoplanet:7.5.2", "geoplanet:7.6.0", "geoplanet:7.8.1", "geoplanet:7.9.0", "geoplanet:7.10.0", "geoplanet:8.0.0", "woeplanet:8.0.0"], "meta:indexed": "2020-08-20T20:53:41.952269", "meta:updated": "2020-08-22T01:53:17.199149", "woe:alias_FRE_S": ["Aerodrome de Lyon-brindas"], "woe:hierarchy": {"continent": 24865675, "country": 23424819, "town": 0, "planet": 1, "county": 12597185, "suburb": 0, "state": 7153329, "region": 0, "localadmin": 22755552}, "woe:timezone_id": 28350911, "woe:hash": "u05k4csxn0xv", "woe:centroid": [4.69761, 45.71257], "geom:latitude": 45.71257, "geom:longitude": 4.69761, "geom:hash": "u05k4csxn0xv", "woe:latitude": 45.71257, "geom:centroid": [4.69761, 45.71257], "woe:longitude": 4.69761, "woe:repo": "woeplanet-airport-fr"}, "geometry": {"coordinates": [4.69761, 45.71257], "type": "Point"}}