{"type": "Feature", "id": 56051921, "properties": {"woe:id": 56051921, "woe:parent_id": 621648, "woe:name": "A\u00e9rodrome de Romorantin-pruniers", "woe:placetype": 14, "woe:placetype_name": "Airport", "woe:lang": "FRE", "iso:country": "FR", "meta:provider": ["geoplanet:7.3.1", "geoplanet:7.3.2", "geoplanet:7.4.0", "geoplanet:7.4.1", "geoplanet:7.5.1", "geoplanet:7.5.2", "geoplanet:7.6.0", "geoplanet:7.8.1", "geoplanet:7.9.0", "geoplanet:7.10.0", "geoplanet:8.0.0", "woeplanet:8.0.0"], "meta:indexed": "2020-08-20T20:53:42.046184", "meta:updated": "2020-08-22T01:53:17.243986", "woe:alias_FRE_S": ["Aerodrome de Romorantin-pruniers"], "woe:hierarchy": {"continent": 24865675, "country": 23424819, "town": 0, "planet": 1, "county": 12597147, "suburb": 0, "state": 7153314, "region": 0, "localadmin": 12644490}, "woe:timezone_id": 28350911, "woe:hash": "u03jntkmndz7", "woe:centroid": [1.69802, 47.314869], "geom:latitude": 47.314869, "geom:longitude": 1.69802, "geom:hash": "u03jntkmndz7", "woe:latitude": 47.314869, "geom:centroid": [1.69802, 47.314869], "woe:longitude": 1.69802, "woe:repo": "woeplanet-airport-fr"}, "geometry": {"coordinates": [1.69802, 47.314869], "type": "Point"}}